[
  {
    "id": "001",
    "category": "functional",
    "description": "Application loads and displays homepage",
    "steps": [
      "Step 1: Navigate to http://localhost:3000",
      "Step 2: Verify page loads without errors",
      "Step 3: Verify login or redirect to predictions page occurs"
    ],
    "passes": true
  },
  {
    "id": "002",
    "category": "functional",
    "description": "User registration with email and password",
    "steps": [
      "Step 1: Navigate to /register",
      "Step 2: Enter valid email address",
      "Step 3: Enter name",
      "Step 4: Enter password (min 6 characters)",
      "Step 5: Confirm password matches",
      "Step 6: Click register button",
      "Step 7: Verify redirect to login or predictions page",
      "Step 8: Verify success message appears"
    ],
    "passes": true
  },
  {
    "id": "003",
    "category": "functional",
    "description": "User login with valid credentials",
    "steps": [
      "Step 1: Navigate to /login",
      "Step 2: Enter registered email address",
      "Step 3: Enter correct password",
      "Step 4: Click login button",
      "Step 5: Verify redirect to /predictions",
      "Step 6: Verify user session is active"
    ],
    "passes": true
  },
  {
    "id": "004",
    "category": "functional",
    "description": "User login fails with invalid credentials",
    "steps": [
      "Step 1: Navigate to /login",
      "Step 2: Enter registered email address",
      "Step 3: Enter incorrect password",
      "Step 4: Click login button",
      "Step 5: Verify error message displays",
      "Step 6: Verify user remains on login page"
    ],
    "passes": true
  },
  {
    "id": "005",
    "category": "functional",
    "description": "Registration prevents duplicate emails",
    "steps": [
      "Step 1: Navigate to /register",
      "Step 2: Enter already registered email",
      "Step 3: Fill other fields",
      "Step 4: Click register button",
      "Step 5: Verify error message 'Email already registered' displays"
    ],
    "passes": true
  },
  {
    "id": "006",
    "category": "functional",
    "description": "User logout functionality",
    "steps": [
      "Step 1: Login as a registered user",
      "Step 2: Navigate to profile or header area",
      "Step 3: Click logout button",
      "Step 4: Verify redirect to login page",
      "Step 5: Verify protected routes are no longer accessible"
    ],
    "passes": true
  },
  {
    "id": "007",
    "category": "functional",
    "description": "Session persists across browser refresh",
    "steps": [
      "Step 1: Login as registered user",
      "Step 2: Navigate to /predictions",
      "Step 3: Refresh the page",
      "Step 4: Verify user is still logged in",
      "Step 5: Verify predictions page still accessible"
    ],
    "passes": true
  },
  {
    "id": "008",
    "category": "functional",
    "description": "Display all 12 groups with 4 teams each",
    "steps": [
      "Step 1: Login as user",
      "Step 2: Navigate to /predictions",
      "Step 3: Verify Groups A through L are visible",
      "Step 4: Verify each group shows 4 teams",
      "Step 5: Verify total of 48 teams displayed"
    ],
    "passes": true
  },
  {
    "id": "009",
    "category": "functional",
    "description": "Display all 104 matches in tournament structure",
    "steps": [
      "Step 1: Login as user",
      "Step 2: Navigate to /predictions",
      "Step 3: Count total number of matches displayed",
      "Step 4: Verify 72 group stage matches",
      "Step 5: Verify 16 Round of 32 matches",
      "Step 6: Verify 8 Round of 16 matches",
      "Step 7: Verify 4 Quarter-final matches",
      "Step 8: Verify 2 Semi-final matches",
      "Step 9: Verify 1 Third-place playoff",
      "Step 10: Verify 1 Final match",
      "Step 11: Total should be 104 matches"
    ],
    "passes": true
  },
  {
    "id": "010",
    "category": "functional",
    "description": "Group stage matches show fixed team matchups",
    "steps": [
      "Step 1: Login as user",
      "Step 2: Navigate to /predictions",
      "Step 3: View group stage matches",
      "Step 4: Verify each group has 6 matches",
      "Step 5: Verify team names are displayed for both home and away"
    ],
    "passes": true
  },
  {
    "id": "011",
    "category": "functional",
    "description": "Knockout matches show placeholder text before group results",
    "steps": [
      "Step 1: Login as user",
      "Step 2: Navigate to /predictions",
      "Step 3: View Round of 32 matches",
      "Step 4: Verify placeholder text like 'Winner Group A' is displayed",
      "Step 5: Verify placeholder text like 'Runner-up Group B' is displayed"
    ],
    "passes": true
  },
  {
    "id": "012",
    "category": "functional",
    "description": "User can enter prediction for a group stage match",
    "steps": [
      "Step 1: Login as user",
      "Step 2: Navigate to /predictions",
      "Step 3: Find a group stage match",
      "Step 4: Enter home team score (e.g., 2)",
      "Step 5: Enter away team score (e.g., 1)",
      "Step 6: Save prediction",
      "Step 7: Verify prediction is saved",
      "Step 8: Refresh page and verify prediction persists"
    ],
    "passes": true
  },
  {
    "id": "013",
    "category": "functional",
    "description": "User can enter predictions for all 104 matches",
    "steps": [
      "Step 1: Login as user",
      "Step 2: Navigate to /predictions",
      "Step 3: Enter predictions for multiple group stage matches",
      "Step 4: Navigate to knockout stage",
      "Step 5: Enter predictions for knockout matches",
      "Step 6: Save all predictions",
      "Step 7: Verify all predictions are saved",
      "Step 8: Verify progress indicator shows completion"
    ],
    "passes": true
  },
  {
    "id": "014",
    "category": "functional",
    "description": "Score input accepts only valid numbers 0-20",
    "steps": [
      "Step 1: Login as user",
      "Step 2: Navigate to /predictions",
      "Step 3: Try entering negative number",
      "Step 4: Verify validation error or prevention",
      "Step 5: Try entering number > 20",
      "Step 6: Verify validation error or prevention",
      "Step 7: Try entering non-integer",
      "Step 8: Verify validation error or prevention",
      "Step 9: Enter valid score 0-20",
      "Step 10: Verify accepted"
    ],
    "passes": true
  },
  {
    "id": "015",
    "category": "functional",
    "description": "Knockout match prediction includes winner selection for draws",
    "steps": [
      "Step 1: Login as user",
      "Step 2: Navigate to knockout matches",
      "Step 3: Select a knockout match",
      "Step 4: Enter a draw score (e.g., 1-1)",
      "Step 5: Verify winner selection appears",
      "Step 6: Select a winner (home or away)",
      "Step 7: Save prediction",
      "Step 8: Verify prediction saved with winner selection"
    ],
    "passes": true
  },
  {
    "id": "016",
    "category": "functional",
    "description": "Progress indicator shows prediction completion percentage",
    "steps": [
      "Step 1: Login as user",
      "Step 2: Navigate to /predictions",
      "Step 3: Verify progress indicator shows 0/104 or equivalent",
      "Step 4: Enter prediction for one match",
      "Step 5: Verify progress updates to 1/104",
      "Step 6: Enter more predictions",
      "Step 7: Verify progress reflects accurate count"
    ],
    "passes": true
  },
  {
    "id": "017",
    "category": "functional",
    "description": "User can edit predictions before deadline",
    "steps": [
      "Step 1: Login as user",
      "Step 2: Navigate to /predictions",
      "Step 3: Enter a prediction (e.g., 2-1)",
      "Step 4: Save the prediction",
      "Step 5: Change the prediction to different score (e.g., 3-0)",
      "Step 6: Save the updated prediction",
      "Step 7: Refresh page",
      "Step 8: Verify new prediction (3-0) is saved"
    ],
    "passes": true
  },
  {
    "id": "018",
    "category": "functional",
    "description": "Predictions locked after deadline",
    "steps": [
      "Step 1: Admin sets deadline to past date",
      "Step 2: Login as regular user",
      "Step 3: Navigate to /predictions",
      "Step 4: Verify prediction inputs are disabled",
      "Step 5: Verify message indicating predictions are locked",
      "Step 6: Attempt to save a prediction",
      "Step 7: Verify save is prevented"
    ],
    "passes": true
  },
  {
    "id": "019",
    "category": "functional",
    "description": "Countdown timer shows time until deadline",
    "steps": [
      "Step 1: Login as user",
      "Step 2: Navigate to /predictions",
      "Step 3: Verify countdown or deadline display is visible",
      "Step 4: Verify countdown shows remaining time"
    ],
    "passes": true
  },
  {
    "id": "020",
    "category": "functional",
    "description": "Admin can access admin dashboard",
    "steps": [
      "Step 1: Login as admin (admin@example.com)",
      "Step 2: Navigate to /admin",
      "Step 3: Verify admin dashboard loads",
      "Step 4: Verify admin navigation options visible"
    ],
    "passes": true
  },
  {
    "id": "021",
    "category": "functional",
    "description": "Regular user cannot access admin pages",
    "steps": [
      "Step 1: Login as regular user",
      "Step 2: Navigate to /admin",
      "Step 3: Verify access denied or redirect to home",
      "Step 4: Navigate to /admin/matches",
      "Step 5: Verify access denied",
      "Step 6: Navigate to /admin/users",
      "Step 7: Verify access denied"
    ],
    "passes": true
  },
  {
    "id": "022",
    "category": "functional",
    "description": "Admin can enter match result for a single match",
    "steps": [
      "Step 1: Login as admin",
      "Step 2: Navigate to /admin/matches",
      "Step 3: Select a group stage match",
      "Step 4: Enter home team score",
      "Step 5: Enter away team score",
      "Step 6: Click save/confirm button",
      "Step 7: Verify result is saved",
      "Step 8: Navigate to /results",
      "Step 9: Verify match result appears"
    ],
    "passes": true
  },
  {
    "id": "023",
    "category": "functional",
    "description": "Admin can edit existing match results",
    "steps": [
      "Step 1: Login as admin",
      "Step 2: Navigate to /admin/matches",
      "Step 3: Select a match with existing result",
      "Step 4: Change the score",
      "Step 5: Confirm and save",
      "Step 6: Verify result is updated",
      "Step 7: Verify points are recalculated"
    ],
    "passes": true
  },
  {
    "id": "024",
    "category": "functional",
    "description": "Admin result entry requires confirmation",
    "steps": [
      "Step 1: Login as admin",
      "Step 2: Navigate to /admin/matches",
      "Step 3: Enter a match result",
      "Step 4: Verify confirmation dialog/step appears",
      "Step 5: Confirm the entry",
      "Step 6: Verify result is saved after confirmation"
    ],
    "passes": true
  },
  {
    "id": "025",
    "category": "functional",
    "description": "Exact score prediction earns 3 points",
    "steps": [
      "Step 1: Login as user and predict 2-1 for a match",
      "Step 2: Login as admin",
      "Step 3: Enter actual result as 2-1",
      "Step 4: View user's points for this match",
      "Step 5: Verify 3 points earned"
    ],
    "passes": true
  },
  {
    "id": "026",
    "category": "functional",
    "description": "Correct result but wrong score earns 1 point",
    "steps": [
      "Step 1: Login as user and predict 2-1 (home win)",
      "Step 2: Login as admin",
      "Step 3: Enter actual result as 3-0 (also home win)",
      "Step 4: View user's points for this match",
      "Step 5: Verify 1 point earned"
    ],
    "passes": true
  },
  {
    "id": "027",
    "category": "functional",
    "description": "Wrong prediction earns 0 points",
    "steps": [
      "Step 1: Login as user and predict 2-1 (home win)",
      "Step 2: Login as admin",
      "Step 3: Enter actual result as 0-2 (away win)",
      "Step 4: View user's points for this match",
      "Step 5: Verify 0 points earned"
    ],
    "passes": true
  },
  {
    "id": "028",
    "category": "functional",
    "description": "Knockout bonus point for correctly predicted qualifier",
    "steps": [
      "Step 1: Complete group stage results to populate Round of 32",
      "Step 2: Login as user who predicted a team that qualified",
      "Step 3: Login as admin and enter knockout result",
      "Step 4: Verify bonus point for correct qualifier prediction"
    ],
    "passes": true
  },
  {
    "id": "029",
    "category": "functional",
    "description": "Points calculated automatically when result entered",
    "steps": [
      "Step 1: Multiple users make predictions for a match",
      "Step 2: Login as admin",
      "Step 3: Enter match result",
      "Step 4: Navigate to leaderboard",
      "Step 5: Verify all user points updated automatically",
      "Step 6: Verify no manual calculation needed"
    ],
    "passes": true
  },
  {
    "id": "030",
    "category": "functional",
    "description": "Group standings calculated correctly",
    "steps": [
      "Step 1: Login as admin",
      "Step 2: Enter all 6 results for Group A",
      "Step 3: View group standings",
      "Step 4: Verify Points calculated correctly (3 for win, 1 for draw)",
      "Step 5: Verify Goal Difference calculated correctly",
      "Step 6: Verify teams ranked by Points, then GD, then GF"
    ],
    "passes": true
  },
  {
    "id": "031",
    "category": "functional",
    "description": "Top 2 from each group auto-populate Round of 32",
    "steps": [
      "Step 1: Login as admin",
      "Step 2: Enter all group stage results for all 12 groups",
      "Step 3: Navigate to knockout bracket",
      "Step 4: Verify Round of 32 teams populated correctly",
      "Step 5: Verify winners are in correct positions",
      "Step 6: Verify runners-up are in correct positions"
    ],
    "passes": true
  },
  {
    "id": "032",
    "category": "functional",
    "description": "Best third-placed teams auto-populate Round of 32",
    "steps": [
      "Step 1: Login as admin",
      "Step 2: Enter all group stage results",
      "Step 3: Verify 8 best third-placed teams calculated",
      "Step 4: Verify these teams placed in correct Round of 32 slots"
    ],
    "passes": true
  },
  {
    "id": "033",
    "category": "functional",
    "description": "Knockout winner automatically advances to next round",
    "steps": [
      "Step 1: Login as admin",
      "Step 2: Enter Round of 32 match result",
      "Step 3: Verify winner automatically appears in Round of 16",
      "Step 4: Enter Round of 16 result",
      "Step 5: Verify winner appears in Quarter-finals"
    ],
    "passes": true
  },
  {
    "id": "034",
    "category": "functional",
    "description": "Leaderboard displays all users ranked by points",
    "steps": [
      "Step 1: Navigate to /leaderboard",
      "Step 2: Verify list of users displayed",
      "Step 3: Verify columns: Rank, Name, Total Points, Exact Scores Count",
      "Step 4: Verify sorted by points (highest first)"
    ],
    "passes": true
  },
  {
    "id": "035",
    "category": "functional",
    "description": "Current user highlighted on leaderboard",
    "steps": [
      "Step 1: Login as a user",
      "Step 2: Navigate to /leaderboard",
      "Step 3: Verify current user's row is highlighted or distinguished",
      "Step 4: Verify easy to identify own position"
    ],
    "passes": true
  },
  {
    "id": "036",
    "category": "functional",
    "description": "Leaderboard filter by tournament phase",
    "steps": [
      "Step 1: Navigate to /leaderboard",
      "Step 2: Click 'All matches' filter",
      "Step 3: Verify total points shown",
      "Step 4: Click 'Group stage only' filter",
      "Step 5: Verify only group stage points shown",
      "Step 6: Click 'Knockout only' filter",
      "Step 7: Verify only knockout points shown"
    ],
    "passes": true
  },
  {
    "id": "037",
    "category": "functional",
    "description": "Leaderboard sortable by different columns",
    "steps": [
      "Step 1: Navigate to /leaderboard",
      "Step 2: Click to sort by points",
      "Step 3: Verify sorted by points",
      "Step 4: Click to sort by exact scores",
      "Step 5: Verify sorted by exact scores count",
      "Step 6: Click to sort by name",
      "Step 7: Verify sorted alphabetically"
    ],
    "passes": true
  },
  {
    "id": "038",
    "category": "functional",
    "description": "Tied users share same rank",
    "steps": [
      "Step 1: Create scenario where two users have same points",
      "Step 2: Navigate to /leaderboard",
      "Step 3: Verify both users show same rank number",
      "Step 4: Verify secondary sort is alphabetical"
    ],
    "passes": true
  },
  {
    "id": "039",
    "category": "functional",
    "description": "Click user on leaderboard to see detailed breakdown",
    "steps": [
      "Step 1: Navigate to /leaderboard",
      "Step 2: Click on a user's name or row",
      "Step 3: Verify detailed prediction breakdown displays",
      "Step 4: Verify match-by-match points visible",
      "Step 5: Verify accuracy percentage shown"
    ],
    "passes": true
  },
  {
    "id": "040",
    "category": "functional",
    "description": "Results page shows completed matches",
    "steps": [
      "Step 1: Navigate to /results",
      "Step 2: Verify only matches with entered results shown",
      "Step 3: Verify real scores displayed",
      "Step 4: Verify matches grouped by matchday or phase"
    ],
    "passes": true
  },
  {
    "id": "041",
    "category": "functional",
    "description": "Results show statistics per match",
    "steps": [
      "Step 1: Enter results for a match (as admin)",
      "Step 2: Navigate to /results",
      "Step 3: View the match result",
      "Step 4: Verify 'X users got exact score' displayed",
      "Step 5: Verify 'Y users got correct result' displayed"
    ],
    "passes": true
  },
  {
    "id": "042",
    "category": "functional",
    "description": "Admin can mark bonus matches",
    "steps": [
      "Step 1: Login as admin",
      "Step 2: Navigate to /admin/settings",
      "Step 3: Select 3-5 matches as bonus matches",
      "Step 4: Save settings",
      "Step 5: Verify matches marked as bonus",
      "Step 6: Navigate to /results",
      "Step 7: Verify bonus matches visually distinct (star/badge)"
    ],
    "passes": true
  },
  {
    "id": "043",
    "category": "functional",
    "description": "Bonus match tracking displays separately",
    "steps": [
      "Step 1: Mark matches as bonus (admin)",
      "Step 2: Enter results for bonus matches",
      "Step 3: Navigate to /leaderboard",
      "Step 4: Verify bonus match section/display visible",
      "Step 5: Verify shows 'X/Y exact on bonus matches' per user"
    ],
    "passes": true
  },
  {
    "id": "044",
    "category": "functional",
    "description": "Admin can view all registered users",
    "steps": [
      "Step 1: Login as admin",
      "Step 2: Navigate to /admin/users",
      "Step 3: Verify list of all users displayed",
      "Step 4: Verify user email and name visible",
      "Step 5: Verify registration date visible"
    ],
    "passes": true
  },
  {
    "id": "045",
    "category": "functional",
    "description": "Admin can reset user password",
    "steps": [
      "Step 1: Login as admin",
      "Step 2: Navigate to /admin/users",
      "Step 3: Select a user",
      "Step 4: Click reset password",
      "Step 5: Verify new password generated or set",
      "Step 6: Test user can login with new password"
    ],
    "passes": true
  },
  {
    "id": "046",
    "category": "functional",
    "description": "Admin can export leaderboard to CSV",
    "steps": [
      "Step 1: Login as admin",
      "Step 2: Navigate to /admin or /admin/users",
      "Step 3: Click export to CSV button",
      "Step 4: Verify CSV file downloads",
      "Step 5: Verify CSV contains rank, name, points data"
    ],
    "passes": true
  },
  {
    "id": "047",
    "category": "functional",
    "description": "Admin can set prediction deadline",
    "steps": [
      "Step 1: Login as admin",
      "Step 2: Navigate to /admin/settings",
      "Step 3: Find deadline setting",
      "Step 4: Change deadline date/time",
      "Step 5: Save settings",
      "Step 6: Verify deadline updated",
      "Step 7: Verify users see new deadline"
    ],
    "passes": true
  },
  {
    "id": "048",
    "category": "functional",
    "description": "Admin can update team names",
    "steps": [
      "Step 1: Login as admin",
      "Step 2: Navigate to /admin/settings or team management",
      "Step 3: Find placeholder team name",
      "Step 4: Update to actual qualified team name",
      "Step 5: Save changes",
      "Step 6: Verify team name updated throughout app"
    ],
    "passes": true
  },
  {
    "id": "049",
    "category": "functional",
    "description": "User profile page accessible",
    "steps": [
      "Step 1: Login as user",
      "Step 2: Navigate to /profile",
      "Step 3: Verify profile page loads",
      "Step 4: Verify user name and email displayed"
    ],
    "passes": true
  },
  {
    "id": "050",
    "category": "functional",
    "description": "User can change password from profile",
    "steps": [
      "Step 1: Login as user",
      "Step 2: Navigate to /profile",
      "Step 3: Enter current password",
      "Step 4: Enter new password",
      "Step 5: Confirm new password",
      "Step 6: Save changes",
      "Step 7: Logout and login with new password",
      "Step 8: Verify login successful"
    ],
    "passes": true
  },
  {
    "id": "051",
    "category": "functional",
    "description": "Default admin account works on first run",
    "steps": [
      "Step 1: Navigate to /login",
      "Step 2: Enter admin@example.com",
      "Step 3: Enter admin123",
      "Step 4: Click login",
      "Step 5: Verify login successful",
      "Step 6: Navigate to /admin",
      "Step 7: Verify admin access granted"
    ],
    "passes": true
  },
  {
    "id": "052",
    "category": "functional",
    "description": "Database seeds 48 teams on first run",
    "steps": [
      "Step 1: Initialize application",
      "Step 2: Login as admin",
      "Step 3: View team list or group stage",
      "Step 4: Count total number of teams",
      "Step 5: Verify 48 teams exist"
    ],
    "passes": true
  },
  {
    "id": "053",
    "category": "functional",
    "description": "Database seeds 104 matches on first run",
    "steps": [
      "Step 1: Initialize application",
      "Step 2: Login as user",
      "Step 3: Navigate to predictions",
      "Step 4: Count total matches across all stages",
      "Step 5: Verify 104 matches exist"
    ],
    "passes": true
  },
  {
    "id": "054",
    "category": "functional",
    "description": "Predictions page filtered by stage works",
    "steps": [
      "Step 1: Login as user",
      "Step 2: Navigate to /predictions/group",
      "Step 3: Verify only group stage matches shown (72)",
      "Step 4: Navigate to /predictions/knockout",
      "Step 5: Verify only knockout matches shown (32)"
    ],
    "passes": true
  },
  {
    "id": "055",
    "category": "functional",
    "description": "Admin bulk entry by matchday",
    "steps": [
      "Step 1: Login as admin",
      "Step 2: Navigate to /admin/matches",
      "Step 3: Select a matchday or date",
      "Step 4: Enter results for all matches on that day",
      "Step 5: Save all at once",
      "Step 6: Verify all results saved correctly"
    ],
    "passes": true
  },
  {
    "id": "056",
    "category": "functional",
    "description": "Leaderboard updates immediately after result entry",
    "steps": [
      "Step 1: Open leaderboard in one tab",
      "Step 2: Login as admin in another tab",
      "Step 3: Enter a match result",
      "Step 4: Refresh leaderboard tab",
      "Step 5: Verify points updated immediately"
    ],
    "passes": true
  },
  {
    "id": "057",
    "category": "functional",
    "description": "Admin manual override for knockout progression",
    "steps": [
      "Step 1: Login as admin",
      "Step 2: Navigate to knockout bracket management",
      "Step 3: Find edge case where manual override needed",
      "Step 4: Manually assign team to bracket slot",
      "Step 5: Save override",
      "Step 6: Verify bracket updated correctly"
    ],
    "passes": true
  },
  {
    "id": "058",
    "category": "style",
    "description": "Login page has proper styling and layout",
    "steps": [
      "Step 1: Navigate to /login",
      "Step 2: Verify centered login form",
      "Step 3: Verify form fields have proper labels",
      "Step 4: Verify login button is visible and styled",
      "Step 5: Verify link to registration page exists"
    ],
    "passes": true
  },
  {
    "id": "059",
    "category": "style",
    "description": "Registration page has proper styling",
    "steps": [
      "Step 1: Navigate to /register",
      "Step 2: Verify centered registration form",
      "Step 3: Verify all required fields labeled",
      "Step 4: Verify register button styled consistently",
      "Step 5: Verify link to login page exists"
    ],
    "passes": true
  },
  {
    "id": "060",
    "category": "style",
    "description": "Navigation header present on all pages",
    "steps": [
      "Step 1: Login as user",
      "Step 2: Navigate to /predictions",
      "Step 3: Verify navigation header present",
      "Step 4: Navigate to /leaderboard",
      "Step 5: Verify same navigation header",
      "Step 6: Navigate to /results",
      "Step 7: Verify navigation header consistent"
    ],
    "passes": true
  },
  {
    "id": "061",
    "category": "style",
    "description": "Navigation includes links to main sections",
    "steps": [
      "Step 1: Login as user",
      "Step 2: View navigation header",
      "Step 3: Verify link to Predictions",
      "Step 4: Verify link to Leaderboard",
      "Step 5: Verify link to Results",
      "Step 6: Verify link to Profile",
      "Step 7: Verify logout option present"
    ],
    "passes": true
  },
  {
    "id": "062",
    "category": "style",
    "description": "Admin navigation shows admin links",
    "steps": [
      "Step 1: Login as admin",
      "Step 2: View navigation header",
      "Step 3: Verify Admin link/section visible",
      "Step 4: Verify admin options accessible from nav"
    ],
    "passes": true
  },
  {
    "id": "063",
    "category": "style",
    "description": "Predictions page layout is organized by groups",
    "steps": [
      "Step 1: Login as user",
      "Step 2: Navigate to /predictions",
      "Step 3: Verify groups are visually separated",
      "Step 4: Verify group headers (A, B, C... L) visible",
      "Step 5: Verify matches within groups are clearly organized"
    ],
    "passes": true
  },
  {
    "id": "064",
    "category": "style",
    "description": "Match prediction inputs are clear and usable",
    "steps": [
      "Step 1: Login as user",
      "Step 2: Navigate to /predictions",
      "Step 3: Verify team names visible on each side",
      "Step 4: Verify score input fields clearly labeled",
      "Step 5: Verify inputs are appropriately sized",
      "Step 6: Verify easy to enter scores"
    ],
    "passes": true
  },
  {
    "id": "065",
    "category": "style",
    "description": "Knockout bracket displays in bracket/tree format",
    "steps": [
      "Step 1: Login as user",
      "Step 2: Navigate to knockout section",
      "Step 3: Verify visual bracket structure",
      "Step 4: Verify progression paths visible",
      "Step 5: Verify Final match at center/end of bracket"
    ],
    "passes": false
  },
  {
    "id": "066",
    "category": "style",
    "description": "Leaderboard table is properly formatted",
    "steps": [
      "Step 1: Navigate to /leaderboard",
      "Step 2: Verify table headers visible",
      "Step 3: Verify alternating row colors or borders",
      "Step 4: Verify rank numbers visible",
      "Step 5: Verify points clearly displayed"
    ],
    "passes": true
  },
  {
    "id": "067",
    "category": "style",
    "description": "Mobile responsive - login page",
    "steps": [
      "Step 1: Set viewport to mobile size (375px width)",
      "Step 2: Navigate to /login",
      "Step 3: Verify form is fully visible",
      "Step 4: Verify inputs are usable",
      "Step 5: Verify button is accessible"
    ],
    "passes": false
  },
  {
    "id": "068",
    "category": "style",
    "description": "Mobile responsive - predictions page",
    "steps": [
      "Step 1: Set viewport to mobile size (375px width)",
      "Step 2: Login as user",
      "Step 3: Navigate to /predictions",
      "Step 4: Verify groups/matches visible without horizontal scroll",
      "Step 5: Verify inputs are usable on mobile"
    ],
    "passes": false
  },
  {
    "id": "069",
    "category": "style",
    "description": "Mobile responsive - leaderboard",
    "steps": [
      "Step 1: Set viewport to mobile size (375px width)",
      "Step 2: Navigate to /leaderboard",
      "Step 3: Verify table is readable (horizontal scroll OK)",
      "Step 4: Verify filter buttons accessible",
      "Step 5: Verify user can see their position"
    ],
    "passes": false
  },
  {
    "id": "070",
    "category": "style",
    "description": "Progress indicator is visually clear",
    "steps": [
      "Step 1: Login as user",
      "Step 2: Navigate to /predictions",
      "Step 3: Verify progress bar or indicator visible",
      "Step 4: Verify completion count displayed (X/104)",
      "Step 5: Verify visual indication of progress (filled bar, percentage)"
    ],
    "passes": true
  },
  {
    "id": "071",
    "category": "style",
    "description": "Error messages are styled and visible",
    "steps": [
      "Step 1: Navigate to /login",
      "Step 2: Submit empty form",
      "Step 3: Verify error message visible",
      "Step 4: Verify error styled in red/warning color",
      "Step 5: Verify error is near relevant field"
    ],
    "passes": true
  },
  {
    "id": "072",
    "category": "style",
    "description": "Success messages are styled and visible",
    "steps": [
      "Step 1: Login as user",
      "Step 2: Save a prediction",
      "Step 3: Verify success message/feedback appears",
      "Step 4: Verify success styled in green/positive color"
    ],
    "passes": true
  },
  {
    "id": "073",
    "category": "style",
    "description": "Bonus matches have distinct visual indicator",
    "steps": [
      "Step 1: Admin marks bonus matches",
      "Step 2: Navigate to /predictions",
      "Step 3: Find bonus match",
      "Step 4: Verify star icon or badge visible",
      "Step 5: Verify clearly distinguishable from regular matches"
    ],
    "passes": true
  },
  {
    "id": "074",
    "category": "style",
    "description": "Admin pages have consistent admin styling",
    "steps": [
      "Step 1: Login as admin",
      "Step 2: Navigate to /admin",
      "Step 3: Verify admin dashboard styled appropriately",
      "Step 4: Navigate to /admin/matches",
      "Step 5: Verify consistent styling with dashboard",
      "Step 6: Navigate to /admin/users",
      "Step 7: Verify consistent admin theme"
    ],
    "passes": true
  },
  {
    "id": "075",
    "category": "style",
    "description": "Loading states displayed during async operations",
    "steps": [
      "Step 1: Login as user",
      "Step 2: Navigate to /predictions",
      "Step 3: Save a prediction",
      "Step 4: Verify loading indicator while saving",
      "Step 5: Verify button disabled during load"
    ],
    "passes": false
  },
  {
    "id": "076",
    "category": "style",
    "description": "Team flags or emojis displayed",
    "steps": [
      "Step 1: Login as user",
      "Step 2: Navigate to /predictions",
      "Step 3: View matches",
      "Step 4: Verify flag emoji or icon next to team name"
    ],
    "passes": true
  },
  {
    "id": "077",
    "category": "style",
    "description": "Results page matches are styled as cards or table",
    "steps": [
      "Step 1: Navigate to /results",
      "Step 2: Verify completed matches displayed in cards or table",
      "Step 3: Verify scores prominently displayed",
      "Step 4: Verify team names visible",
      "Step 5: Verify statistics visible per match"
    ],
    "passes": true
  },
  {
    "id": "078",
    "category": "functional",
    "description": "Complete user journey - registration to full predictions",
    "steps": [
      "Step 1: Navigate to /register",
      "Step 2: Create new account with unique email",
      "Step 3: Login with new account",
      "Step 4: Navigate to /predictions",
      "Step 5: Enter predictions for 10 group stage matches",
      "Step 6: Navigate to knockout stage",
      "Step 7: Enter predictions for 5 knockout matches",
      "Step 8: Verify progress indicator updates",
      "Step 9: Navigate to /leaderboard",
      "Step 10: Verify user appears on leaderboard",
      "Step 11: Navigate to /profile",
      "Step 12: Verify profile shows correct info",
      "Step 13: Logout and login again",
      "Step 14: Verify predictions persisted"
    ],
    "passes": false
  },
  {
    "id": "079",
    "category": "functional",
    "description": "Complete admin journey - entering full matchday results",
    "steps": [
      "Step 1: Login as admin",
      "Step 2: Navigate to /admin/matches",
      "Step 3: Enter results for 8 group stage matches",
      "Step 4: Verify all results saved",
      "Step 5: Navigate to /results",
      "Step 6: Verify all 8 results displayed",
      "Step 7: Navigate to /leaderboard",
      "Step 8: Verify points calculated for all users",
      "Step 9: Navigate to /admin/settings",
      "Step 10: Mark one completed match as bonus match",
      "Step 11: Verify bonus tracking updates"
    ],
    "passes": false
  },
  {
    "id": "080",
    "category": "functional",
    "description": "Complete tournament simulation - group to knockout",
    "steps": [
      "Step 1: Create 3 test users with predictions",
      "Step 2: Login as admin",
      "Step 3: Enter all 6 results for Group A",
      "Step 4: Enter all 6 results for Group B",
      "Step 5: Verify group standings calculated",
      "Step 6: Enter results for remaining groups (simulated)",
      "Step 7: Verify Round of 32 teams populated",
      "Step 8: Enter one Round of 32 result",
      "Step 9: Verify winner advances to Round of 16",
      "Step 10: Check leaderboard reflects all points",
      "Step 11: Verify detailed breakdown for each user"
    ],
    "passes": false
  },
  {
    "id": "081",
    "category": "functional",
    "description": "Draw prediction with penalty winner selection",
    "steps": [
      "Step 1: Login as user",
      "Step 2: Navigate to knockout match",
      "Step 3: Predict 2-2 draw",
      "Step 4: Verify winner selection dropdown appears",
      "Step 5: Select home team as winner",
      "Step 6: Save prediction",
      "Step 7: Login as admin",
      "Step 8: Enter actual result 2-2 with away team winning",
      "Step 9: Verify user gets 1 point for correct draw",
      "Step 10: Verify user does not get bonus for wrong winner"
    ],
    "passes": true
  },
  {
    "id": "082",
    "category": "functional",
    "description": "Multiple users competing - points differentiation",
    "steps": [
      "Step 1: Create user1 and predict Match 1 as 2-1",
      "Step 2: Create user2 and predict Match 1 as 3-1",
      "Step 3: Create user3 and predict Match 1 as 0-2",
      "Step 4: Login as admin and enter result 2-1",
      "Step 5: Check leaderboard",
      "Step 6: Verify user1 has 3 points (exact)",
      "Step 7: Verify user2 has 1 point (correct result)",
      "Step 8: Verify user3 has 0 points (wrong result)",
      "Step 9: Verify ranking order is user1, user2, user3"
    ],
    "passes": true
  },
  {
    "id": "083",
    "category": "functional",
    "description": "Prediction page URL routing works",
    "steps": [
      "Step 1: Login as user",
      "Step 2: Navigate directly to /predictions",
      "Step 3: Verify page loads",
      "Step 4: Navigate directly to /predictions/group",
      "Step 5: Verify group stage filter applied",
      "Step 6: Navigate directly to /predictions/knockout",
      "Step 7: Verify knockout filter applied"
    ],
    "passes": true
  },
  {
    "id": "084",
    "category": "functional",
    "description": "Protected routes redirect to login",
    "steps": [
      "Step 1: Ensure logged out",
      "Step 2: Navigate directly to /predictions",
      "Step 3: Verify redirect to /login",
      "Step 4: Navigate directly to /profile",
      "Step 5: Verify redirect to /login",
      "Step 6: Navigate directly to /admin",
      "Step 7: Verify redirect to /login"
    ],
    "passes": true
  },
  {
    "id": "085",
    "category": "functional",
    "description": "Third place playoff in bracket",
    "steps": [
      "Step 1: Login as user",
      "Step 2: Navigate to knockout predictions",
      "Step 3: Find Third-place playoff match",
      "Step 4: Verify it shows semi-final losers placeholder",
      "Step 5: Enter prediction",
      "Step 6: Save and verify persistence"
    ],
    "passes": true
  },
  {
    "id": "086",
    "category": "functional",
    "description": "Final match in bracket",
    "steps": [
      "Step 1: Login as user",
      "Step 2: Navigate to knockout predictions",
      "Step 3: Find Final match",
      "Step 4: Verify it shows semi-final winners placeholder",
      "Step 5: Enter prediction",
      "Step 6: Save and verify persistence"
    ],
    "passes": true
  },
  {
    "id": "087",
    "category": "functional",
    "description": "Scoring breakdown visible per match",
    "steps": [
      "Step 1: User makes prediction for a match",
      "Step 2: Admin enters result",
      "Step 3: Login as user",
      "Step 4: Navigate to view their predictions/results",
      "Step 5: Verify can see: predicted score, actual score, points earned",
      "Step 6: Verify scoring reason visible (exact/correct result/wrong)"
    ],
    "passes": true
  },
  {
    "id": "088",
    "category": "functional",
    "description": "Accuracy percentage calculated correctly",
    "steps": [
      "Step 1: User predicts 10 matches",
      "Step 2: Admin enters results for 10 matches",
      "Step 3: User gets 3 exact, 4 correct result, 3 wrong",
      "Step 4: View user detail on leaderboard",
      "Step 5: Verify accuracy shows 70% (7/10 correct predictions)"
    ],
    "passes": true
  },
  {
    "id": "089",
    "category": "style",
    "description": "Tablet responsive - predictions page",
    "steps": [
      "Step 1: Set viewport to tablet size (768px width)",
      "Step 2: Login as user",
      "Step 3: Navigate to /predictions",
      "Step 4: Verify layout adjusts appropriately",
      "Step 5: Verify all functionality accessible"
    ],
    "passes": false
  },
  {
    "id": "090",
    "category": "style",
    "description": "Deadline countdown styling",
    "steps": [
      "Step 1: Login as user",
      "Step 2: Navigate to /predictions",
      "Step 3: View deadline countdown",
      "Step 4: Verify countdown is prominently displayed",
      "Step 5: Verify urgency styling when close to deadline (optional)"
    ],
    "passes": true
  },
  {
    "id": "091",
    "category": "functional",
    "description": "API validates session on all protected endpoints",
    "steps": [
      "Step 1: Try to access /api/predictions without session",
      "Step 2: Verify 401 Unauthorized response",
      "Step 3: Try to access /api/admin/matches without session",
      "Step 4: Verify 401 Unauthorized response",
      "Step 5: Login and verify same endpoints work"
    ],
    "passes": true
  },
  {
    "id": "092",
    "category": "functional",
    "description": "Admin API endpoints check admin role",
    "steps": [
      "Step 1: Login as regular user",
      "Step 2: Try to POST to /api/admin/matches",
      "Step 3: Verify 403 Forbidden response",
      "Step 4: Login as admin",
      "Step 5: POST to same endpoint",
      "Step 6: Verify success"
    ],
    "passes": true
  },
  {
    "id": "093",
    "category": "functional",
    "description": "Homepage redirect logic",
    "steps": [
      "Step 1: Navigate to / when logged out",
      "Step 2: Verify redirect to /login",
      "Step 3: Login as user",
      "Step 4: Navigate to /",
      "Step 5: Verify redirect to /predictions"
    ],
    "passes": true
  },
  {
    "id": "094",
    "category": "functional",
    "description": "Group standings tiebreaker logic",
    "steps": [
      "Step 1: Login as admin",
      "Step 2: Enter group results that create tied teams (same points)",
      "Step 3: Verify tiebreaker by Goal Difference",
      "Step 4: If still tied, verify tiebreaker by Goals For",
      "Step 5: Verify correct team advances"
    ],
    "passes": true
  },
  {
    "id": "095",
    "category": "functional",
    "description": "Concurrent prediction saves don't cause conflicts",
    "steps": [
      "Step 1: Login as user in two browser tabs",
      "Step 2: Edit same match prediction in both tabs",
      "Step 3: Save from first tab",
      "Step 4: Save from second tab",
      "Step 5: Refresh both tabs",
      "Step 6: Verify last save wins without errors"
    ],
    "passes": true
  },
  {
    "id": "096",
    "category": "style",
    "description": "Confirmation dialogs styled appropriately",
    "steps": [
      "Step 1: Login as admin",
      "Step 2: Navigate to /admin/matches",
      "Step 3: Enter a result and submit",
      "Step 4: Verify confirmation dialog appears",
      "Step 5: Verify dialog is modal and styled",
      "Step 6: Verify confirm/cancel buttons visible"
    ],
    "passes": false
  },
  {
    "id": "097",
    "category": "functional",
    "description": "Match numbers are unique and sequential",
    "steps": [
      "Step 1: Login as user",
      "Step 2: Navigate to all matches",
      "Step 3: Verify match numbers 1-104 exist",
      "Step 4: Verify no duplicate match numbers",
      "Step 5: Verify matches ordered correctly by number"
    ],
    "passes": true
  },
  {
    "id": "098",
    "category": "functional",
    "description": "Tournament deadline stored in database",
    "steps": [
      "Step 1: Login as admin",
      "Step 2: Set a new deadline",
      "Step 3: Restart the server",
      "Step 4: Login and check deadline",
      "Step 5: Verify deadline persisted"
    ],
    "passes": true
  },
  {
    "id": "099",
    "category": "functional",
    "description": "Predictions locked message after deadline",
    "steps": [
      "Step 1: Admin sets deadline to past",
      "Step 2: Login as user",
      "Step 3: Navigate to /predictions",
      "Step 4: Verify 'Predictions locked' message displayed",
      "Step 5: Verify message is clear and prominent"
    ],
    "passes": true
  },
  {
    "id": "100",
    "category": "style",
    "description": "Footer or copyright notice present",
    "steps": [
      "Step 1: Navigate to any page",
      "Step 2: Scroll to bottom",
      "Step 3: Verify footer exists",
      "Step 4: Verify relevant info (copyright, year)"
    ],
    "passes": true
  }
]